{"cameraMode":{"drawMode":0,"name":"Shaded","section":"Shading Mode"},"sceneLighting":false,"audioPlay":false,"sceneViewState":{"showFog":true,"showMaterialUpdate":false,"showSkybox":false,"showFlares":true,"showImageEffects":true,"showParticleSystems":true},"in2DMode":false,"pivot":{"x":687.8382568359375,"y":117.97738647460938,"z":10.9075927734375},"rotation":{"x":-0.034799739718437198,"y":-0.012894722633063794,"z":0.00044894980965182185,"w":-0.9993112683296204},"size":344.7151184082031,"orthographic":false}